{
	"credit": "Made with Blockbench",
	"texture_size": [64, 64],
	"textures": {
		"0": "block/texture",
		"particle": "block/texture"
	},
	"elements": [
		{
			"from": [0, 8, 7],
			"to": [16, 16, 16],
			"rotation": {"angle": 0, "axis": "y", "origin": [0, 8, 0]},
			"faces": {
				"north": {"uv": [0, 2, 4, 4], "texture": "#0"},
				"east": {"uv": [2, 2, 4, 4], "texture": "#0"},
				"south": {"uv": [0, 2, 4, 4], "texture": "#0"},
				"west": {"uv": [2, 2, 4, 4], "texture": "#0"},
				"up": {"uv": [4, 2, 0, 0], "texture": "#0"},
				"down": {"uv": [4, 0, 0, 4], "texture": "#0"}
			}
		},
		{
			"from": [0, 0, 0],
			"to": [16, 8, 16],
			"faces": {
				"north": {"uv": [0, 2, 4, 4], "texture": "#0"},
				"east": {"uv": [0, 2, 4, 4], "texture": "#0"},
				"south": {"uv": [0, 2, 4, 4], "texture": "#0"},
				"west": {"uv": [0, 2, 4, 4], "texture": "#0"},
				"up": {"uv": [4, 4, 0, 0], "texture": "#0"},
				"down": {"uv": [4, 0, 0, 4], "texture": "#0"}
			}
		}
	],
	"groups": [
		{
			"name": "stairs",
			"origin": [0, 0, 0],
			"color": 0,
			"children": [0, 1]
		}
	]
}